concretefhe_compiler-0.0.10-py3.9-nspkg.pth
concretefhe/compiler/__init__.py
concretefhe/compiler/file.py
concretefhe_compiler-0.0.10.dist-info/LICENSE
concretefhe_compiler-0.0.10.dist-info/METADATA
concretefhe_compiler-0.0.10.dist-info/WHEEL
concretefhe_compiler-0.0.10.dist-info/namespace_packages.txt
concretefhe_compiler-0.0.10.dist-info/top_level.txt
concretefhe_compiler-0.0.10.dist-info/RECORD
